LICENSE
MANIFEST.in
README.rst
setup.py
pinyin/Mandarin.dat
pinyin/__init__.py
pinyin/_compat.py
pinyin/cedict.py
pinyin/cedict.txt.gz
pinyin/cmd.py
pinyin/pinyin.py
pinyin_hitalent.egg-info/PKG-INFO
pinyin_hitalent.egg-info/SOURCES.txt
pinyin_hitalent.egg-info/dependency_links.txt
pinyin_hitalent.egg-info/entry_points.txt
pinyin_hitalent.egg-info/top_level.txt